{
  "action_encoding": {
    "formula": "action = prescription_index * n_receiver_actions + receiver_action",
    "solver_jpo_action_offset": 1,
    "state_zero_bit": "most_significant"
  },
  "bounds": {
    "gap": 1.2735233184908328,
    "lower_objective": 3.1614875789338956,
    "lower_values": [
      3.3405190380645298,
      2.8941166015006985,
      3.3405190380645298,
      3.3405190380645298,
      3.3405190380645298,
      2.71273271984456
    ],
    "root_gap": 1.2735233184908321,
    "root_lower_objective": 3.161487578933896,
    "root_upper_objective": 4.435010897424728,
    "upper_objective": 4.435010897424728,
    "upper_values": [
      4.661816265660944,
      4.324324760033987,
      4.496194637760995,
      4.496194637760995,
      4.496194637760995,
      4.135340445570455
    ]
  },
  "initialization": {
    "initial_beliefs": [
      [
        1.0,
        0.0,
        0.0,
        0.0,
        0.0,
        0.0
      ],
      [
        0.0,
        1.0,
        0.0,
        0.0,
        0.0,
        0.0
      ],
      [
        0.0,
        0.0,
        1.0,
        0.0,
        0.0,
        0.0
      ],
      [
        0.0,
        0.0,
        0.0,
        1.0,
        0.0,
        0.0
      ],
      [
        0.0,
        0.0,
        0.0,
        0.0,
        1.0,
        0.0
      ],
      [
        0.0,
        0.0,
        0.0,
        0.0,
        0.0,
        1.0
      ]
    ],
    "initial_weights": [
      0.16666666666666666,
      0.16666666666666666,
      0.16666666666666666,
      0.16666666666666666,
      0.16666666666666666,
      0.16666666666666666
    ],
    "kind": "single synthetic root revealing a uniformly sampled physical state",
    "root_value_scale": "V_root / gamma, gamma=0.9"
  },
  "model": {
    "beta": 1.1111111111111112,
    "epsilon": 0.06,
    "gamma": 0.9,
    "mdp_density": 0.5,
    "mdp_seed": 1111,
    "mdp_sha256": "580f9fa806b22e34e0f0d1010a1012409199158e69e3f71c129e1c5119fb8d6a",
    "n_jpo_actions": 128,
    "n_prescriptions": 64,
    "n_receiver_actions": 2,
    "n_states": 6
  },
  "runtime": {
    "julia": "1.12.6",
    "native_sarsop": "0.1.4",
    "pomdp_tools": "1.1.0",
    "pomdps": "1.0.0"
  },
  "solver": {
    "delta": 0.0001,
    "export_beliefs": false,
    "initial_bound_max_time": 30.0,
    "initial_bound_residual": 1e-08,
    "initial_upper_bound": "fully_observable",
    "kappa": 0.5,
    "max_steps": 1000000,
    "max_time": 700.0,
    "precision": 0.01,
    "prune_threshold": 0.1,
    "search_epsilon": 0.01,
    "use_binning": true
  },
  "training": {
    "alpha_count": 33,
    "belief_count": 5522749,
    "elapsed_seconds": 703.4869811534882,
    "history": [
      {
        "elapsed_seconds": 1.4066696166992188e-05,
        "initial_gap": 115.12945975387242,
        "initial_lower_objective": -110.00000000000004,
        "initial_upper_objective": 5.129459753872374,
        "iteration": 0,
        "root_gap": 103.61651377848519,
        "root_lower": -99.00000000000004,
        "root_upper": 4.616513778485137
      },
      {
        "elapsed_seconds": 0.007737159729003906,
        "initial_gap": 2.0853507394540527,
        "initial_lower_objective": 3.044109014418322,
        "initial_upper_objective": 5.129459753872374,
        "iteration": 1,
        "root_gap": 1.8768156655086474,
        "root_lower": 2.7396981129764897,
        "root_upper": 4.616513778485137
      },
      {
        "elapsed_seconds": 0.03664708137512207,
        "initial_gap": 1.9955445835200178,
        "initial_lower_objective": 3.1339151689817837,
        "initial_upper_objective": 5.129459752501802,
        "iteration": 2,
        "root_gap": 1.7959901251680161,
        "root_lower": 2.8205236520836054,
        "root_upper": 4.616513777251622
      },
      {
        "elapsed_seconds": 0.09498119354248047,
        "initial_gap": 1.9804814220343312,
        "initial_lower_objective": 3.1489783290968987,
        "initial_upper_objective": 5.12945975113123,
        "iteration": 3,
        "root_gap": 1.7824332798308982,
        "root_lower": 2.834080496187209,
        "root_upper": 4.616513776018107
      },
      {
        "elapsed_seconds": 0.16920709609985352,
        "initial_gap": 1.9723521348156936,
        "initial_lower_objective": 3.1571076163155363,
        "initial_upper_objective": 5.12945975113123,
        "iteration": 4,
        "root_gap": 1.7751169213341242,
        "root_lower": 2.8413968546839827,
        "root_upper": 4.616513776018107
      },
      {
        "elapsed_seconds": 0.2687861919403076,
        "initial_gap": 1.9718998605107303,
        "initial_lower_objective": 3.1575598906204996,
        "initial_upper_objective": 5.12945975113123,
        "iteration": 5,
        "root_gap": 1.7747098744596572,
        "root_lower": 2.8418039015584498,
        "root_upper": 4.616513776018107
      },
      {
        "elapsed_seconds": 0.3953711986541748,
        "initial_gap": 1.9703970173555632,
        "initial_lower_objective": 3.1590627337756665,
        "initial_upper_objective": 5.12945975113123,
        "iteration": 6,
        "root_gap": 1.7733573156200069,
        "root_lower": 2.8431564603981,
        "root_upper": 4.616513776018107
      },
      {
        "elapsed_seconds": 0.5373890399932861,
        "initial_gap": 1.969037097909836,
        "initial_lower_objective": 3.160422653221394,
        "initial_upper_objective": 5.12945975113123,
        "iteration": 7,
        "root_gap": 1.7721333881188523,
        "root_lower": 2.8443803878992546,
        "root_upper": 4.616513776018107
      },
      {
        "elapsed_seconds": 0.7144320011138916,
        "initial_gap": 1.969037097909836,
        "initial_lower_objective": 3.160422653221394,
        "initial_upper_objective": 5.12945975113123,
        "iteration": 8,
        "root_gap": 1.7721333881188523,
        "root_lower": 2.8443803878992546,
        "root_upper": 4.616513776018107
      },
      {
        "elapsed_seconds": 1.0752241611480713,
        "initial_gap": 1.969037097909836,
        "initial_lower_objective": 3.160422653221394,
        "initial_upper_objective": 5.12945975113123,
        "iteration": 9,
        "root_gap": 1.7721333881188523,
        "root_lower": 2.8443803878992546,
        "root_upper": 4.616513776018107
      },
      {
        "elapsed_seconds": 1.3358781337738037,
        "initial_gap": 1.969037097909836,
        "initial_lower_objective": 3.160422653221394,
        "initial_upper_objective": 5.12945975113123,
        "iteration": 10,
        "root_gap": 1.7721333881188523,
        "root_lower": 2.8443803878992546,
        "root_upper": 4.616513776018107
      },
      {
        "elapsed_seconds": 1.6374280452728271,
        "initial_gap": 1.939275193147931,
        "initial_lower_objective": 3.160422653221394,
        "initial_upper_objective": 5.099697846369325,
        "iteration": 11,
        "root_gap": 1.745347673833138,
        "root_lower": 2.8443803878992546,
        "root_upper": 4.589728061732393
      },
      {
        "elapsed_seconds": 1.956299066543579,
        "initial_gap": 1.9235217429450626,
        "initial_lower_objective": 3.160452639084321,
        "initial_upper_objective": 5.083974382029384,
        "iteration": 12,
        "root_gap": 1.7311695686505564,
        "root_lower": 2.844407375175889,
        "root_upper": 4.575576943826445
      },
      {
        "elapsed_seconds": 2.3482720851898193,
        "initial_gap": 1.8880348046407618,
        "initial_lower_objective": 3.160452639084321,
        "initial_upper_objective": 5.048487443725083,
        "iteration": 13,
        "root_gap": 1.6992313241766857,
        "root_lower": 2.844407375175889,
        "root_upper": 4.543638699352575
      },
      {
        "elapsed_seconds": 2.741680145263672,
        "initial_gap": 1.846987057252099,
        "initial_lower_objective": 3.1606523857034263,
        "initial_upper_objective": 5.007639442955525,
        "iteration": 14,
        "root_gap": 1.6622883515268891,
        "root_lower": 2.8445871471330837,
        "root_upper": 4.506875498659973
      },
      {
        "elapsed_seconds": 3.017747163772583,
        "initial_gap": 1.8469410849176244,
        "initial_lower_objective": 3.1606983580379007,
        "initial_upper_objective": 5.007639442955525,
        "iteration": 15,
        "root_gap": 1.662246976425862,
        "root_lower": 2.844628522234111,
        "root_upper": 4.506875498659973
      },
      {
        "elapsed_seconds": 3.9343011379241943,
        "initial_gap": 1.8469378375114005,
        "initial_lower_objective": 3.1607016054441246,
        "initial_upper_objective": 5.007639442955525,
        "iteration": 16,
        "root_gap": 1.6622440537602605,
        "root_lower": 2.8446314448997123,
        "root_upper": 4.506875498659973
      },
      {
        "elapsed_seconds": 4.4294750690460205,
        "initial_gap": 1.8468839776804695,
        "initial_lower_objective": 3.160755465275056,
        "initial_upper_objective": 5.007639442955525,
        "iteration": 17,
        "root_gap": 1.6621955799124226,
        "root_lower": 2.84467991874755,
        "root_upper": 4.506875498659973
      },
      {
        "elapsed_seconds": 4.959777116775513,
        "initial_gap": 1.8468839776804695,
        "initial_lower_objective": 3.160755465275056,
        "initial_upper_objective": 5.007639442955525,
        "iteration": 18,
        "root_gap": 1.6621955799124226,
        "root_lower": 2.84467991874755,
        "root_upper": 4.506875498659973
      },
      {
        "elapsed_seconds": 5.576372146606445,
        "initial_gap": 1.8468305672328598,
        "initial_lower_objective": 3.1608088757226653,
        "initial_upper_objective": 5.007639442955525,
        "iteration": 19,
        "root_gap": 1.6621475105095738,
        "root_lower": 2.844727988150399,
        "root_upper": 4.506875498659973
      },
      {
        "elapsed_seconds": 6.195449113845825,
        "initial_gap": 1.8467806055069773,
        "initial_lower_objective": 3.160858837448548,
        "initial_upper_objective": 5.007639442955525,
        "iteration": 20,
        "root_gap": 1.6621025449562796,
        "root_lower": 2.844772953703693,
        "root_upper": 4.506875498659973
      },
      {
        "elapsed_seconds": 6.870690107345581,
        "initial_gap": 1.8467737415865912,
        "initial_lower_objective": 3.160865701368934,
        "initial_upper_objective": 5.007639442955525,
        "iteration": 21,
        "root_gap": 1.662096367427932,
        "root_lower": 2.8447791312320407,
        "root_upper": 4.506875498659973
      },
      {
        "elapsed_seconds": 7.516174077987671,
        "initial_gap": 1.8170071344339498,
        "initial_lower_objective": 3.1608704037596707,
        "initial_upper_objective": 4.977877538193621,
        "iteration": 22,
        "root_gap": 1.6353064209905548,
        "root_lower": 2.8447833633837036,
        "root_upper": 4.480089784374258
      },
      {
        "elapsed_seconds": 8.3077712059021,
        "initial_gap": 1.7997819709160643,
        "initial_lower_objective": 3.1608761773589085,
        "initial_upper_objective": 4.960658148274972,
        "iteration": 23,
        "root_gap": 1.619803773824458,
        "root_lower": 2.8447885596230176,
        "root_upper": 4.4645923334474755
      },
      {
        "elapsed_seconds": 9.151315212249756,
        "initial_gap": 1.7997802440854322,
        "initial_lower_objective": 3.1608779041895403,
        "initial_upper_objective": 4.960658148274972,
        "iteration": 24,
        "root_gap": 1.619802219676889,
        "root_lower": 2.8447901137705864,
        "root_upper": 4.4645923334474755
      },
      {
        "elapsed_seconds": 10.042757034301758,
        "initial_gap": 1.7994899999547274,
        "initial_lower_objective": 3.1611681483202454,
        "initial_upper_objective": 4.960658148274972,
        "iteration": 25,
        "root_gap": 1.6195409999592547,
        "root_lower": 2.845051333488221,
        "root_upper": 4.4645923334474755
      },
      {
        "elapsed_seconds": 10.994723081588745,
        "initial_gap": 1.7994899999547274,
        "initial_lower_objective": 3.1611681483202454,
        "initial_upper_objective": 4.960658148274972,
        "iteration": 26,
        "root_gap": 1.6195409999592547,
        "root_lower": 2.845051333488221,
        "root_upper": 4.4645923334474755
      },
      {
        "elapsed_seconds": 11.99601411819458,
        "initial_gap": 1.7994899999547274,
        "initial_lower_objective": 3.1611681483202454,
        "initial_upper_objective": 4.960658148274972,
        "iteration": 27,
        "root_gap": 1.6195409999592547,
        "root_lower": 2.845051333488221,
        "root_upper": 4.4645923334474755
      },
      {
        "elapsed_seconds": 13.188338994979858,
        "initial_gap": 1.7994899999547274,
        "initial_lower_objective": 3.1611681483202454,
        "initial_upper_objective": 4.960658148274972,
        "iteration": 28,
        "root_gap": 1.6195409999592547,
        "root_lower": 2.845051333488221,
        "root_upper": 4.4645923334474755
      },
      {
        "elapsed_seconds": 14.358806133270264,
        "initial_gap": 1.7994817868936706,
        "initial_lower_objective": 3.161176361381302,
        "initial_upper_objective": 4.960658148274972,
        "iteration": 29,
        "root_gap": 1.6195336082043035,
        "root_lower": 2.845058725243172,
        "root_upper": 4.4645923334474755
      },
      {
        "elapsed_seconds": 15.527637004852295,
        "initial_gap": 1.7994817868936706,
        "initial_lower_objective": 3.161176361381302,
        "initial_upper_objective": 4.960658148274972,
        "iteration": 30,
        "root_gap": 1.6195336082043035,
        "root_lower": 2.845058725243172,
        "root_upper": 4.4645923334474755
      },
      {
        "elapsed_seconds": 16.713394165039062,
        "initial_gap": 1.7994817868936706,
        "initial_lower_objective": 3.161176361381302,
        "initial_upper_objective": 4.960658148274972,
        "iteration": 31,
        "root_gap": 1.6195336082043035,
        "root_lower": 2.845058725243172,
        "root_upper": 4.4645923334474755
      },
      {
        "elapsed_seconds": 17.939718008041382,
        "initial_gap": 1.7994817868936706,
        "initial_lower_objective": 3.161176361381302,
        "initial_upper_objective": 4.960658148274972,
        "iteration": 32,
        "root_gap": 1.6195336082043035,
        "root_lower": 2.845058725243172,
        "root_upper": 4.4645923334474755
      },
      {
        "elapsed_seconds": 19.235164165496826,
        "initial_gap": 1.7994817868936706,
        "initial_lower_objective": 3.161176361381302,
        "initial_upper_objective": 4.960658148274972,
        "iteration": 33,
        "root_gap": 1.6195336082043035,
        "root_lower": 2.845058725243172,
        "root_upper": 4.4645923334474755
      },
      {
        "elapsed_seconds": 20.636680126190186,
        "initial_gap": 1.7994817868936706,
        "initial_lower_objective": 3.161176361381302,
        "initial_upper_objective": 4.960658148274972,
        "iteration": 34,
        "root_gap": 1.6195336082043035,
        "root_lower": 2.845058725243172,
        "root_upper": 4.4645923334474755
      },
      {
        "elapsed_seconds": 21.979268074035645,
        "initial_gap": 1.7994817868936706,
        "initial_lower_objective": 3.161176361381302,
        "initial_upper_objective": 4.960658148274972,
        "iteration": 35,
        "root_gap": 1.6195336082043035,
        "root_lower": 2.845058725243172,
        "root_upper": 4.4645923334474755
      },
      {
        "elapsed_seconds": 23.43774104118347,
        "initial_gap": 1.7994817868936706,
        "initial_lower_objective": 3.161176361381302,
        "initial_upper_objective": 4.960658148274972,
        "iteration": 36,
        "root_gap": 1.6195336082043035,
        "root_lower": 2.845058725243172,
        "root_upper": 4.4645923334474755
      },
      {
        "elapsed_seconds": 24.95504403114319,
        "initial_gap": 1.7994817868936706,
        "initial_lower_objective": 3.161176361381302,
        "initial_upper_objective": 4.960658148274972,
        "iteration": 37,
        "root_gap": 1.6195336082043035,
        "root_lower": 2.845058725243172,
        "root_upper": 4.4645923334474755
      },
      {
        "elapsed_seconds": 26.520766019821167,
        "initial_gap": 1.7994817868936706,
        "initial_lower_objective": 3.161176361381302,
        "initial_upper_objective": 4.960658148274972,
        "iteration": 38,
        "root_gap": 1.6195336082043035,
        "root_lower": 2.845058725243172,
        "root_upper": 4.4645923334474755
      },
      {
        "elapsed_seconds": 28.015595197677612,
        "initial_gap": 1.7697198821317657,
        "initial_lower_objective": 3.161176361381302,
        "initial_upper_objective": 4.930896243513068,
        "iteration": 39,
        "root_gap": 1.592747893918589,
        "root_lower": 2.845058725243172,
        "root_upper": 4.437806619161761
      },
      {
        "elapsed_seconds": 29.71649408340454,
        "initial_gap": 1.7697198821317657,
        "initial_lower_objective": 3.161176361381302,
        "initial_upper_objective": 4.930896243513068,
        "iteration": 40,
        "root_gap": 1.592747893918589,
        "root_lower": 2.845058725243172,
        "root_upper": 4.437806619161761
      },
      {
        "elapsed_seconds": 31.636487007141113,
        "initial_gap": 1.7697198821317657,
        "initial_lower_objective": 3.161176361381302,
        "initial_upper_objective": 4.930896243513068,
        "iteration": 41,
        "root_gap": 1.592747893918589,
        "root_lower": 2.845058725243172,
        "root_upper": 4.437806619161761
      },
      {
        "elapsed_seconds": 34.228066205978394,
        "initial_gap": 1.7697198821317657,
        "initial_lower_objective": 3.161176361381302,
        "initial_upper_objective": 4.930896243513068,
        "iteration": 42,
        "root_gap": 1.592747893918589,
        "root_lower": 2.845058725243172,
        "root_upper": 4.437806619161761
      },
      {
        "elapsed_seconds": 35.99116516113281,
        "initial_gap": 1.7697198821317657,
        "initial_lower_objective": 3.161176361381302,
        "initial_upper_objective": 4.930896243513068,
        "iteration": 43,
        "root_gap": 1.592747893918589,
        "root_lower": 2.845058725243172,
        "root_upper": 4.437806619161761
      },
      {
        "elapsed_seconds": 37.801547050476074,
        "initial_gap": 1.7697198821317657,
        "initial_lower_objective": 3.161176361381302,
        "initial_upper_objective": 4.930896243513068,
        "iteration": 44,
        "root_gap": 1.592747893918589,
        "root_lower": 2.845058725243172,
        "root_upper": 4.437806619161761
      },
      {
        "elapsed_seconds": 39.66733908653259,
        "initial_gap": 1.7697198821317657,
        "initial_lower_objective": 3.161176361381302,
        "initial_upper_objective": 4.930896243513068,
        "iteration": 45,
        "root_gap": 1.592747893918589,
        "root_lower": 2.845058725243172,
        "root_upper": 4.437806619161761
      },
      {
        "elapsed_seconds": 41.584182024002075,
        "initial_gap": 1.7697198821317657,
        "initial_lower_objective": 3.161176361381302,
        "initial_upper_objective": 4.930896243513068,
        "iteration": 46,
        "root_gap": 1.592747893918589,
        "root_lower": 2.845058725243172,
        "root_upper": 4.437806619161761
      },
      {
        "elapsed_seconds": 43.591896057128906,
        "initial_gap": 1.7547380325610669,
        "initial_lower_objective": 3.161176361381302,
        "initial_upper_objective": 4.915914393942369,
        "iteration": 47,
        "root_gap": 1.5792642293049601,
        "root_lower": 2.845058725243172,
        "root_upper": 4.424322954548132
      },
      {
        "elapsed_seconds": 45.66737198829651,
        "initial_gap": 1.7547380325610669,
        "initial_lower_objective": 3.161176361381302,
        "initial_upper_objective": 4.915914393942369,
        "iteration": 48,
        "root_gap": 1.5792642293049601,
        "root_lower": 2.845058725243172,
        "root_upper": 4.424322954548132
      },
      {
        "elapsed_seconds": 47.691739082336426,
        "initial_gap": 1.754709870814907,
        "initial_lower_objective": 3.161204523127462,
        "initial_upper_objective": 4.915914393942369,
        "iteration": 49,
        "root_gap": 1.5792388837334164,
        "root_lower": 2.845084070814716,
        "root_upper": 4.424322954548132
      },
      {
        "elapsed_seconds": 49.77582597732544,
        "initial_gap": 1.754596323156539,
        "initial_lower_objective": 3.16131807078583,
        "initial_upper_objective": 4.915914393942369,
        "iteration": 50,
        "root_gap": 1.579136690840885,
        "root_lower": 2.845186263707247,
        "root_upper": 4.424322954548132
      },
      {
        "elapsed_seconds": 50.88910913467407,
        "initial_gap": 1.754596323156539,
        "initial_lower_objective": 3.16131807078583,
        "initial_upper_objective": 4.915914393942369,
        "iteration": 51,
        "root_gap": 1.579136690840885,
        "root_lower": 2.845186263707247,
        "root_upper": 4.424322954548132
      },
      {
        "elapsed_seconds": 53.17537498474121,
        "initial_gap": 1.754596323156539,
        "initial_lower_objective": 3.16131807078583,
        "initial_upper_objective": 4.915914393942369,
        "iteration": 52,
        "root_gap": 1.579136690840885,
        "root_lower": 2.845186263707247,
        "root_upper": 4.424322954548132
      },
      {
        "elapsed_seconds": 55.43652009963989,
        "initial_gap": 1.754596323156539,
        "initial_lower_objective": 3.16131807078583,
        "initial_upper_objective": 4.915914393942369,
        "iteration": 53,
        "root_gap": 1.579136690840885,
        "root_lower": 2.845186263707247,
        "root_upper": 4.424322954548132
      },
      {
        "elapsed_seconds": 57.842435121536255,
        "initial_gap": 1.754596323156539,
        "initial_lower_objective": 3.16131807078583,
        "initial_upper_objective": 4.915914393942369,
        "iteration": 54,
        "root_gap": 1.579136690840885,
        "root_lower": 2.845186263707247,
        "root_upper": 4.424322954548132
      },
      {
        "elapsed_seconds": 60.46851205825806,
        "initial_gap": 1.754596323156539,
        "initial_lower_objective": 3.16131807078583,
        "initial_upper_objective": 4.915914393942369,
        "iteration": 55,
        "root_gap": 1.579136690840885,
        "root_lower": 2.845186263707247,
        "root_upper": 4.424322954548132
      },
      {
        "elapsed_seconds": 63.420929193496704,
        "initial_gap": 1.7545314459926602,
        "initial_lower_objective": 3.1613829479497086,
        "initial_upper_objective": 4.915914393942369,
        "iteration": 56,
        "root_gap": 1.5790783013933942,
        "root_lower": 2.845244653154738,
        "root_upper": 4.424322954548132
      },
      {
        "elapsed_seconds": 66.27568697929382,
        "initial_gap": 1.7545314459926602,
        "initial_lower_objective": 3.1613829479497086,
        "initial_upper_objective": 4.915914393942369,
        "iteration": 57,
        "root_gap": 1.5790783013933942,
        "root_lower": 2.845244653154738,
        "root_upper": 4.424322954548132
      },
      {
        "elapsed_seconds": 69.00496101379395,
        "initial_gap": 1.7545314459926602,
        "initial_lower_objective": 3.1613829479497086,
        "initial_upper_objective": 4.915914393942369,
        "iteration": 58,
        "root_gap": 1.5790783013933942,
        "root_lower": 2.845244653154738,
        "root_upper": 4.424322954548132
      },
      {
        "elapsed_seconds": 72.2215461730957,
        "initial_gap": 1.7545314459926602,
        "initial_lower_objective": 3.1613829479497086,
        "initial_upper_objective": 4.915914393942369,
        "iteration": 59,
        "root_gap": 1.5790783013933942,
        "root_lower": 2.845244653154738,
        "root_upper": 4.424322954548132
      },
      {
        "elapsed_seconds": 75.48092317581177,
        "initial_gap": 1.7545314459926602,
        "initial_lower_objective": 3.1613829479497086,
        "initial_upper_objective": 4.915914393942369,
        "iteration": 60,
        "root_gap": 1.5790783013933942,
        "root_lower": 2.845244653154738,
        "root_upper": 4.424322954548132
      },
      {
        "elapsed_seconds": 78.37628507614136,
        "initial_gap": 1.7545314459926602,
        "initial_lower_objective": 3.1613829479497086,
        "initial_upper_objective": 4.915914393942369,
        "iteration": 61,
        "root_gap": 1.5790783013933942,
        "root_lower": 2.845244653154738,
        "root_upper": 4.424322954548132
      },
      {
        "elapsed_seconds": 81.23379707336426,
        "initial_gap": 1.7545314459926602,
        "initial_lower_objective": 3.1613829479497086,
        "initial_upper_objective": 4.915914393942369,
        "iteration": 62,
        "root_gap": 1.5790783013933942,
        "root_lower": 2.845244653154738,
        "root_upper": 4.424322954548132
      },
      {
        "elapsed_seconds": 84.077632188797,
        "initial_gap": 1.7247695412307553,
        "initial_lower_objective": 3.1613829479497086,
        "initial_upper_objective": 4.886152489180464,
        "iteration": 63,
        "root_gap": 1.5522925871076798,
        "root_lower": 2.845244653154738,
        "root_upper": 4.397537240262418
      },
      {
        "elapsed_seconds": 86.83095407485962,
        "initial_gap": 1.7247390954764898,
        "initial_lower_objective": 3.161413393703974,
        "initial_upper_objective": 4.886152489180464,
        "iteration": 64,
        "root_gap": 1.552265185928841,
        "root_lower": 2.8452720543335768,
        "root_upper": 4.397537240262418
      },
      {
        "elapsed_seconds": 89.6053581237793,
        "initial_gap": 1.7247390954764898,
        "initial_lower_objective": 3.161413393703974,
        "initial_upper_objective": 4.886152489180464,
        "iteration": 65,
        "root_gap": 1.552265185928841,
        "root_lower": 2.8452720543335768,
        "root_upper": 4.397537240262418
      },
      {
        "elapsed_seconds": 92.62216305732727,
        "initial_gap": 1.7247390954764898,
        "initial_lower_objective": 3.161413393703974,
        "initial_upper_objective": 4.886152489180464,
        "iteration": 66,
        "root_gap": 1.552265185928841,
        "root_lower": 2.8452720543335768,
        "root_upper": 4.397537240262418
      },
      {
        "elapsed_seconds": 95.70514512062073,
        "initial_gap": 1.7247390954764898,
        "initial_lower_objective": 3.161413393703974,
        "initial_upper_objective": 4.886152489180464,
        "iteration": 67,
        "root_gap": 1.552265185928841,
        "root_lower": 2.8452720543335768,
        "root_upper": 4.397537240262418
      },
      {
        "elapsed_seconds": 98.83034300804138,
        "initial_gap": 1.7247390954764898,
        "initial_lower_objective": 3.161413393703974,
        "initial_upper_objective": 4.886152489180464,
        "iteration": 68,
        "root_gap": 1.552265185928841,
        "root_lower": 2.8452720543335768,
        "root_upper": 4.397537240262418
      },
      {
        "elapsed_seconds": 103.23408102989197,
        "initial_gap": 1.7247390954764898,
        "initial_lower_objective": 3.161413393703974,
        "initial_upper_objective": 4.886152489180464,
        "iteration": 69,
        "root_gap": 1.552265185928841,
        "root_lower": 2.8452720543335768,
        "root_upper": 4.397537240262418
      },
      {
        "elapsed_seconds": 106.58816409111023,
        "initial_gap": 1.7247390954764898,
        "initial_lower_objective": 3.161413393703974,
        "initial_upper_objective": 4.886152489180464,
        "iteration": 70,
        "root_gap": 1.552265185928841,
        "root_lower": 2.8452720543335768,
        "root_upper": 4.397537240262418
      },
      {
        "elapsed_seconds": 110.6686851978302,
        "initial_gap": 1.7247390954764898,
        "initial_lower_objective": 3.161413393703974,
        "initial_upper_objective": 4.886152489180464,
        "iteration": 71,
        "root_gap": 1.552265185928841,
        "root_lower": 2.8452720543335768,
        "root_upper": 4.397537240262418
      },
      {
        "elapsed_seconds": 114.39857006072998,
        "initial_gap": 1.7247390954764898,
        "initial_lower_objective": 3.161413393703974,
        "initial_upper_objective": 4.886152489180464,
        "iteration": 72,
        "root_gap": 1.552265185928841,
        "root_lower": 2.8452720543335768,
        "root_upper": 4.397537240262418
      },
      {
        "elapsed_seconds": 117.9085111618042,
        "initial_gap": 1.7247390954764898,
        "initial_lower_objective": 3.161413393703974,
        "initial_upper_objective": 4.886152489180464,
        "iteration": 73,
        "root_gap": 1.552265185928841,
        "root_lower": 2.8452720543335768,
        "root_upper": 4.397537240262418
      },
      {
        "elapsed_seconds": 121.59440612792969,
        "initial_gap": 1.7247390954764898,
        "initial_lower_objective": 3.161413393703974,
        "initial_upper_objective": 4.886152489180464,
        "iteration": 74,
        "root_gap": 1.552265185928841,
        "root_lower": 2.8452720543335768,
        "root_upper": 4.397537240262418
      },
      {
        "elapsed_seconds": 125.32618618011475,
        "initial_gap": 1.7247390954764898,
        "initial_lower_objective": 3.161413393703974,
        "initial_upper_objective": 4.886152489180464,
        "iteration": 75,
        "root_gap": 1.552265185928841,
        "root_lower": 2.8452720543335768,
        "root_upper": 4.397537240262418
      },
      {
        "elapsed_seconds": 129.18515706062317,
        "initial_gap": 1.6699712054233526,
        "initial_lower_objective": 3.161413393703974,
        "initial_upper_objective": 4.831384599127326,
        "iteration": 76,
        "root_gap": 1.5029740848810174,
        "root_lower": 2.8452720543335768,
        "root_upper": 4.348246139214594
      },
      {
        "elapsed_seconds": 133.2121241092682,
        "initial_gap": 1.6699712054233526,
        "initial_lower_objective": 3.161413393703974,
        "initial_upper_objective": 4.831384599127326,
        "iteration": 77,
        "root_gap": 1.5029740848810174,
        "root_lower": 2.8452720543335768,
        "root_upper": 4.348246139214594
      },
      {
        "elapsed_seconds": 134.52102708816528,
        "initial_gap": 1.6699712054233526,
        "initial_lower_objective": 3.161413393703974,
        "initial_upper_objective": 4.831384599127326,
        "iteration": 78,
        "root_gap": 1.5029740848810174,
        "root_lower": 2.8452720543335768,
        "root_upper": 4.348246139214594
      },
      {
        "elapsed_seconds": 138.70778703689575,
        "initial_gap": 1.6402093006614487,
        "initial_lower_objective": 3.161413393703974,
        "initial_upper_objective": 4.801622694365423,
        "iteration": 79,
        "root_gap": 1.4761883705953038,
        "root_lower": 2.8452720543335768,
        "root_upper": 4.321460424928881
      },
      {
        "elapsed_seconds": 143.27005219459534,
        "initial_gap": 1.6402093006614487,
        "initial_lower_objective": 3.161413393703974,
        "initial_upper_objective": 4.801622694365423,
        "iteration": 80,
        "root_gap": 1.4761883705953038,
        "root_lower": 2.8452720543335768,
        "root_upper": 4.321460424928881
      },
      {
        "elapsed_seconds": 147.763916015625,
        "initial_gap": 1.6402093006614487,
        "initial_lower_objective": 3.161413393703974,
        "initial_upper_objective": 4.801622694365423,
        "iteration": 81,
        "root_gap": 1.4761883705953038,
        "root_lower": 2.8452720543335768,
        "root_upper": 4.321460424928881
      },
      {
        "elapsed_seconds": 152.56612515449524,
        "initial_gap": 1.6402093006614487,
        "initial_lower_objective": 3.161413393703974,
        "initial_upper_objective": 4.801622694365423,
        "iteration": 82,
        "root_gap": 1.4761883705953038,
        "root_lower": 2.8452720543335768,
        "root_upper": 4.321460424928881
      },
      {
        "elapsed_seconds": 157.65434503555298,
        "initial_gap": 1.6402093006614487,
        "initial_lower_objective": 3.161413393703974,
        "initial_upper_objective": 4.801622694365423,
        "iteration": 83,
        "root_gap": 1.4761883705953038,
        "root_lower": 2.8452720543335768,
        "root_upper": 4.321460424928881
      },
      {
        "elapsed_seconds": 161.90572810173035,
        "initial_gap": 1.6402093006614487,
        "initial_lower_objective": 3.161413393703974,
        "initial_upper_objective": 4.801622694365423,
        "iteration": 84,
        "root_gap": 1.4761883705953038,
        "root_lower": 2.8452720543335768,
        "root_upper": 4.321460424928881
      },
      {
        "elapsed_seconds": 166.75382208824158,
        "initial_gap": 1.6402093006614487,
        "initial_lower_objective": 3.161413393703974,
        "initial_upper_objective": 4.801622694365423,
        "iteration": 85,
        "root_gap": 1.4761883705953038,
        "root_lower": 2.8452720543335768,
        "root_upper": 4.321460424928881
      },
      {
        "elapsed_seconds": 171.2847990989685,
        "initial_gap": 1.6401950130458631,
        "initial_lower_objective": 3.1614276813195596,
        "initial_upper_objective": 4.801622694365423,
        "iteration": 86,
        "root_gap": 1.476175511741277,
        "root_lower": 2.8452849131876037,
        "root_upper": 4.321460424928881
      },
      {
        "elapsed_seconds": 175.55432200431824,
        "initial_gap": 1.6401950130458631,
        "initial_lower_objective": 3.1614276813195596,
        "initial_upper_objective": 4.801622694365423,
        "iteration": 87,
        "root_gap": 1.476175511741277,
        "root_lower": 2.8452849131876037,
        "root_upper": 4.321460424928881
      },
      {
        "elapsed_seconds": 180.59842705726624,
        "initial_gap": 1.5361498409299301,
        "initial_lower_objective": 3.1614317041827107,
        "initial_upper_objective": 4.697581545112641,
        "iteration": 88,
        "root_gap": 1.382534856836937,
        "root_lower": 2.84528853376444,
        "root_upper": 4.227823390601377
      },
      {
        "elapsed_seconds": 185.92404413223267,
        "initial_gap": 1.5361471588862303,
        "initial_lower_objective": 3.1614343862264107,
        "initial_upper_objective": 4.697581545112641,
        "iteration": 89,
        "root_gap": 1.3825324429976074,
        "root_lower": 2.8452909476037695,
        "root_upper": 4.227823390601377
      },
      {
        "elapsed_seconds": 190.7696681022644,
        "initial_gap": 1.5361471588862303,
        "initial_lower_objective": 3.1614343862264107,
        "initial_upper_objective": 4.697581545112641,
        "iteration": 90,
        "root_gap": 1.3825324429976074,
        "root_lower": 2.8452909476037695,
        "root_upper": 4.227823390601377
      },
      {
        "elapsed_seconds": 195.97707200050354,
        "initial_gap": 1.5361471588862303,
        "initial_lower_objective": 3.1614343862264107,
        "initial_upper_objective": 4.697581545112641,
        "iteration": 91,
        "root_gap": 1.3825324429976074,
        "root_lower": 2.8452909476037695,
        "root_upper": 4.227823390601377
      },
      {
        "elapsed_seconds": 200.62009119987488,
        "initial_gap": 1.5361471588862303,
        "initial_lower_objective": 3.1614343862264107,
        "initial_upper_objective": 4.697581545112641,
        "iteration": 92,
        "root_gap": 1.3825324429976074,
        "root_lower": 2.8452909476037695,
        "root_upper": 4.227823390601377
      },
      {
        "elapsed_seconds": 205.54059219360352,
        "initial_gap": 1.5361471588862303,
        "initial_lower_objective": 3.1614343862264107,
        "initial_upper_objective": 4.697581545112641,
        "iteration": 93,
        "root_gap": 1.3825324429976074,
        "root_lower": 2.8452909476037695,
        "root_upper": 4.227823390601377
      },
      {
        "elapsed_seconds": 210.6776762008667,
        "initial_gap": 1.5361471588862303,
        "initial_lower_objective": 3.1614343862264107,
        "initial_upper_objective": 4.697581545112641,
        "iteration": 94,
        "root_gap": 1.3825324429976074,
        "root_lower": 2.8452909476037695,
        "root_upper": 4.227823390601377
      },
      {
        "elapsed_seconds": 216.07749104499817,
        "initial_gap": 1.5361471588862303,
        "initial_lower_objective": 3.1614343862264107,
        "initial_upper_objective": 4.697581545112641,
        "iteration": 95,
        "root_gap": 1.3825324429976074,
        "root_lower": 2.8452909476037695,
        "root_upper": 4.227823390601377
      },
      {
        "elapsed_seconds": 221.62212204933167,
        "initial_gap": 1.5361471588862303,
        "initial_lower_objective": 3.1614343862264107,
        "initial_upper_objective": 4.697581545112641,
        "iteration": 96,
        "root_gap": 1.3825324429976074,
        "root_lower": 2.8452909476037695,
        "root_upper": 4.227823390601377
      },
      {
        "elapsed_seconds": 227.51292300224304,
        "initial_gap": 1.5361450700419905,
        "initial_lower_objective": 3.1614364750706505,
        "initial_upper_objective": 4.697581545112641,
        "iteration": 97,
        "root_gap": 1.3825305630377915,
        "root_lower": 2.8452928275635854,
        "root_upper": 4.227823390601377
      },
      {
        "elapsed_seconds": 233.72529315948486,
        "initial_gap": 1.5361445487811314,
        "initial_lower_objective": 3.1614369963315094,
        "initial_upper_objective": 4.697581545112641,
        "iteration": 98,
        "root_gap": 1.3825300939030183,
        "root_lower": 2.8452932966983586,
        "root_upper": 4.227823390601377
      },
      {
        "elapsed_seconds": 239.67214703559875,
        "initial_gap": 1.536142791199628,
        "initial_lower_objective": 3.161438753913013,
        "initial_upper_objective": 4.697581545112641,
        "iteration": 99,
        "root_gap": 1.382528512079665,
        "root_lower": 2.845294878521712,
        "root_upper": 4.227823390601377
      },
      {
        "elapsed_seconds": 245.32595801353455,
        "initial_gap": 1.536142791199628,
        "initial_lower_objective": 3.161438753913013,
        "initial_upper_objective": 4.697581545112641,
        "iteration": 100,
        "root_gap": 1.382528512079665,
        "root_lower": 2.845294878521712,
        "root_upper": 4.227823390601377
      },
      {
        "elapsed_seconds": 251.63321900367737,
        "initial_gap": 1.536142791199628,
        "initial_lower_objective": 3.161438753913013,
        "initial_upper_objective": 4.697581545112641,
        "iteration": 101,
        "root_gap": 1.382528512079665,
        "root_lower": 2.845294878521712,
        "root_upper": 4.227823390601377
      },
      {
        "elapsed_seconds": 257.55130410194397,
        "initial_gap": 1.536142791199628,
        "initial_lower_objective": 3.161438753913013,
        "initial_upper_objective": 4.697581545112641,
        "iteration": 102,
        "root_gap": 1.382528512079665,
        "root_lower": 2.845294878521712,
        "root_upper": 4.227823390601377
      },
      {
        "elapsed_seconds": 263.91625118255615,
        "initial_gap": 1.536142791199628,
        "initial_lower_objective": 3.161438753913013,
        "initial_upper_objective": 4.697581545112641,
        "iteration": 103,
        "root_gap": 1.382528512079665,
        "root_lower": 2.845294878521712,
        "root_upper": 4.227823390601377
      },
      {
        "elapsed_seconds": 270.3168921470642,
        "initial_gap": 1.5063333586121934,
        "initial_lower_objective": 3.1614862817385427,
        "initial_upper_objective": 4.667819640350736,
        "iteration": 104,
        "root_gap": 1.3557000227509741,
        "root_lower": 2.8453376535646884,
        "root_upper": 4.2010376763156625
      },
      {
        "elapsed_seconds": 277.01557207107544,
        "initial_gap": 1.5063328365091175,
        "initial_lower_objective": 3.161486803841618,
        "initial_upper_objective": 4.667819640350736,
        "iteration": 105,
        "root_gap": 1.3556995528582059,
        "root_lower": 2.8453381234574566,
        "root_upper": 4.2010376763156625
      },
      {
        "elapsed_seconds": 283.69198203086853,
        "initial_gap": 1.5063328365091175,
        "initial_lower_objective": 3.161486803841618,
        "initial_upper_objective": 4.667819640350736,
        "iteration": 106,
        "root_gap": 1.3556995528582059,
        "root_lower": 2.8453381234574566,
        "root_upper": 4.2010376763156625
      },
      {
        "elapsed_seconds": 290.22577714920044,
        "initial_gap": 1.5063328365091175,
        "initial_lower_objective": 3.161486803841618,
        "initial_upper_objective": 4.667819640350736,
        "iteration": 107,
        "root_gap": 1.3556995528582059,
        "root_lower": 2.8453381234574566,
        "root_upper": 4.2010376763156625
      },
      {
        "elapsed_seconds": 296.9832901954651,
        "initial_gap": 1.5063328365091175,
        "initial_lower_objective": 3.161486803841618,
        "initial_upper_objective": 4.667819640350736,
        "iteration": 108,
        "root_gap": 1.3556995528582059,
        "root_lower": 2.8453381234574566,
        "root_upper": 4.2010376763156625
      },
      {
        "elapsed_seconds": 304.20506715774536,
        "initial_gap": 1.5063328365091175,
        "initial_lower_objective": 3.161486803841618,
        "initial_upper_objective": 4.667819640350736,
        "iteration": 109,
        "root_gap": 1.3556995528582059,
        "root_lower": 2.8453381234574566,
        "root_upper": 4.2010376763156625
      },
      {
        "elapsed_seconds": 312.0132541656494,
        "initial_gap": 1.5063328365091175,
        "initial_lower_objective": 3.161486803841618,
        "initial_upper_objective": 4.667819640350736,
        "iteration": 110,
        "root_gap": 1.3556995528582059,
        "root_lower": 2.8453381234574566,
        "root_upper": 4.2010376763156625
      },
      {
        "elapsed_seconds": 313.4130220413208,
        "initial_gap": 1.5063328365091175,
        "initial_lower_objective": 3.161486803841618,
        "initial_upper_objective": 4.667819640350736,
        "iteration": 111,
        "root_gap": 1.3556995528582059,
        "root_lower": 2.8453381234574566,
        "root_upper": 4.2010376763156625
      },
      {
        "elapsed_seconds": 320.3521091938019,
        "initial_gap": 1.502159871741372,
        "initial_lower_objective": 3.161486803841618,
        "initial_upper_objective": 4.66364667558299,
        "iteration": 112,
        "root_gap": 1.351943884567235,
        "root_lower": 2.8453381234574566,
        "root_upper": 4.1972820080246915
      },
      {
        "elapsed_seconds": 327.2013041973114,
        "initial_gap": 1.502159871741372,
        "initial_lower_objective": 3.161486803841618,
        "initial_upper_objective": 4.66364667558299,
        "iteration": 113,
        "root_gap": 1.351943884567235,
        "root_lower": 2.8453381234574566,
        "root_upper": 4.1972820080246915
      },
      {
        "elapsed_seconds": 333.80951619148254,
        "initial_gap": 1.502159871741372,
        "initial_lower_objective": 3.161486803841618,
        "initial_upper_objective": 4.66364667558299,
        "iteration": 114,
        "root_gap": 1.351943884567235,
        "root_lower": 2.8453381234574566,
        "root_upper": 4.1972820080246915
      },
      {
        "elapsed_seconds": 340.82033109664917,
        "initial_gap": 1.502159871741372,
        "initial_lower_objective": 3.161486803841618,
        "initial_upper_objective": 4.66364667558299,
        "iteration": 115,
        "root_gap": 1.351943884567235,
        "root_lower": 2.8453381234574566,
        "root_upper": 4.1972820080246915
      },
      {
        "elapsed_seconds": 347.62960720062256,
        "initial_gap": 1.502159871741372,
        "initial_lower_objective": 3.161486803841618,
        "initial_upper_objective": 4.66364667558299,
        "iteration": 116,
        "root_gap": 1.351943884567235,
        "root_lower": 2.8453381234574566,
        "root_upper": 4.1972820080246915
      },
      {
        "elapsed_seconds": 354.0791871547699,
        "initial_gap": 1.502159871741372,
        "initial_lower_objective": 3.161486803841618,
        "initial_upper_objective": 4.66364667558299,
        "iteration": 117,
        "root_gap": 1.351943884567235,
        "root_lower": 2.8453381234574566,
        "root_upper": 4.1972820080246915
      },
      {
        "elapsed_seconds": 362.25471806526184,
        "initial_gap": 1.502159871741372,
        "initial_lower_objective": 3.161486803841618,
        "initial_upper_objective": 4.66364667558299,
        "iteration": 118,
        "root_gap": 1.351943884567235,
        "root_lower": 2.8453381234574566,
        "root_upper": 4.1972820080246915
      },
      {
        "elapsed_seconds": 369.36124420166016,
        "initial_gap": 1.502159871741372,
        "initial_lower_objective": 3.161486803841618,
        "initial_upper_objective": 4.66364667558299,
        "iteration": 119,
        "root_gap": 1.351943884567235,
        "root_lower": 2.8453381234574566,
        "root_upper": 4.1972820080246915
      },
      {
        "elapsed_seconds": 376.9507451057434,
        "initial_gap": 1.4029003468822518,
        "initial_lower_objective": 3.161486803841618,
        "initial_upper_objective": 4.56438715072387,
        "iteration": 120,
        "root_gap": 1.2626103121940266,
        "root_lower": 2.8453381234574566,
        "root_upper": 4.107948435651483
      },
      {
        "elapsed_seconds": 389.3564200401306,
        "initial_gap": 1.4029003468822518,
        "initial_lower_objective": 3.161486803841618,
        "initial_upper_objective": 4.56438715072387,
        "iteration": 121,
        "root_gap": 1.2626103121940266,
        "root_lower": 2.8453381234574566,
        "root_upper": 4.107948435651483
      },
      {
        "elapsed_seconds": 397.4208722114563,
        "initial_gap": 1.4029003468822518,
        "initial_lower_objective": 3.161486803841618,
        "initial_upper_objective": 4.56438715072387,
        "iteration": 122,
        "root_gap": 1.2626103121940266,
        "root_lower": 2.8453381234574566,
        "root_upper": 4.107948435651483
      },
      {
        "elapsed_seconds": 405.2899980545044,
        "initial_gap": 1.4029003468822518,
        "initial_lower_objective": 3.161486803841618,
        "initial_upper_objective": 4.56438715072387,
        "iteration": 123,
        "root_gap": 1.2626103121940266,
        "root_lower": 2.8453381234574566,
        "root_upper": 4.107948435651483
      },
      {
        "elapsed_seconds": 414.4910571575165,
        "initial_gap": 1.4029003468822518,
        "initial_lower_objective": 3.161486803841618,
        "initial_upper_objective": 4.56438715072387,
        "iteration": 124,
        "root_gap": 1.2626103121940266,
        "root_lower": 2.8453381234574566,
        "root_upper": 4.107948435651483
      },
      {
        "elapsed_seconds": 421.4619641304016,
        "initial_gap": 1.4029003468822518,
        "initial_lower_objective": 3.161486803841618,
        "initial_upper_objective": 4.56438715072387,
        "iteration": 125,
        "root_gap": 1.2626103121940266,
        "root_lower": 2.8453381234574566,
        "root_upper": 4.107948435651483
      },
      {
        "elapsed_seconds": 428.552531003952,
        "initial_gap": 1.4029003468822518,
        "initial_lower_objective": 3.161486803841618,
        "initial_upper_objective": 4.56438715072387,
        "iteration": 126,
        "root_gap": 1.2626103121940266,
        "root_lower": 2.8453381234574566,
        "root_upper": 4.107948435651483
      },
      {
        "elapsed_seconds": 435.5130741596222,
        "initial_gap": 1.4029003468822518,
        "initial_lower_objective": 3.161486803841618,
        "initial_upper_objective": 4.56438715072387,
        "iteration": 127,
        "root_gap": 1.2626103121940266,
        "root_lower": 2.8453381234574566,
        "root_upper": 4.107948435651483
      },
      {
        "elapsed_seconds": 443.4729151725769,
        "initial_gap": 1.4029003468822518,
        "initial_lower_objective": 3.161486803841618,
        "initial_upper_objective": 4.56438715072387,
        "iteration": 128,
        "root_gap": 1.2626103121940266,
        "root_lower": 2.8453381234574566,
        "root_upper": 4.107948435651483
      },
      {
        "elapsed_seconds": 451.84787917137146,
        "initial_gap": 1.3715620227630905,
        "initial_lower_objective": 3.161486803841618,
        "initial_upper_objective": 4.533048826604709,
        "iteration": 129,
        "root_gap": 1.2344058204867814,
        "root_lower": 2.8453381234574566,
        "root_upper": 4.079743943944238
      },
      {
        "elapsed_seconds": 460.26443910598755,
        "initial_gap": 1.3715620227630905,
        "initial_lower_objective": 3.161486803841618,
        "initial_upper_objective": 4.533048826604709,
        "iteration": 130,
        "root_gap": 1.2344058204867814,
        "root_lower": 2.8453381234574566,
        "root_upper": 4.079743943944238
      },
      {
        "elapsed_seconds": 462.4434599876404,
        "initial_gap": 1.3715620227630905,
        "initial_lower_objective": 3.161486803841618,
        "initial_upper_objective": 4.533048826604709,
        "iteration": 131,
        "root_gap": 1.2344058204867814,
        "root_lower": 2.8453381234574566,
        "root_upper": 4.079743943944238
      },
      {
        "elapsed_seconds": 471.4293100833893,
        "initial_gap": 1.3715620227630905,
        "initial_lower_objective": 3.161486803841618,
        "initial_upper_objective": 4.533048826604709,
        "iteration": 132,
        "root_gap": 1.2344058204867814,
        "root_lower": 2.8453381234574566,
        "root_upper": 4.079743943944238
      },
      {
        "elapsed_seconds": 481.0174341201782,
        "initial_gap": 1.3715620227630905,
        "initial_lower_objective": 3.161486803841618,
        "initial_upper_objective": 4.533048826604709,
        "iteration": 133,
        "root_gap": 1.2344058204867814,
        "root_lower": 2.8453381234574566,
        "root_upper": 4.079743943944238
      },
      {
        "elapsed_seconds": 490.3627212047577,
        "initial_gap": 1.3715620227630905,
        "initial_lower_objective": 3.161486803841618,
        "initial_upper_objective": 4.533048826604709,
        "iteration": 134,
        "root_gap": 1.2344058204867814,
        "root_lower": 2.8453381234574566,
        "root_upper": 4.079743943944238
      },
      {
        "elapsed_seconds": 493.61605501174927,
        "initial_gap": 1.3715620227630905,
        "initial_lower_objective": 3.161486803841618,
        "initial_upper_objective": 4.533048826604709,
        "iteration": 135,
        "root_gap": 1.2344058204867814,
        "root_lower": 2.8453381234574566,
        "root_upper": 4.079743943944238
      },
      {
        "elapsed_seconds": 501.67304015159607,
        "initial_gap": 1.3715620227630905,
        "initial_lower_objective": 3.161486803841618,
        "initial_upper_objective": 4.533048826604709,
        "iteration": 136,
        "root_gap": 1.2344058204867814,
        "root_lower": 2.8453381234574566,
        "root_upper": 4.079743943944238
      },
      {
        "elapsed_seconds": 512.3553001880646,
        "initial_gap": 1.2848124028033168,
        "initial_lower_objective": 3.161486803841618,
        "initial_upper_objective": 4.446299206644935,
        "iteration": 137,
        "root_gap": 1.156331162522985,
        "root_lower": 2.8453381234574566,
        "root_upper": 4.001669285980442
      },
      {
        "elapsed_seconds": 521.5535399913788,
        "initial_gap": 1.2848122355362395,
        "initial_lower_objective": 3.1614869711086957,
        "initial_upper_objective": 4.446299206644935,
        "iteration": 138,
        "root_gap": 1.1563310119826156,
        "root_lower": 2.845338273997826,
        "root_upper": 4.001669285980442
      },
      {
        "elapsed_seconds": 532.2089881896973,
        "initial_gap": 1.2848121577880864,
        "initial_lower_objective": 3.1614870488568485,
        "initial_upper_objective": 4.446299206644935,
        "iteration": 139,
        "root_gap": 1.1563309420092778,
        "root_lower": 2.845338343971164,
        "root_upper": 4.001669285980442
      },
      {
        "elapsed_seconds": 543.3718152046204,
        "initial_gap": 1.2848119440346444,
        "initial_lower_objective": 3.161487262610291,
        "initial_upper_objective": 4.446299206644935,
        "iteration": 140,
        "root_gap": 1.1563307496311799,
        "root_lower": 2.845338536349262,
        "root_upper": 4.001669285980442
      },
      {
        "elapsed_seconds": 554.6547009944916,
        "initial_gap": 1.2848117287432197,
        "initial_lower_objective": 3.1614874779017157,
        "initial_upper_objective": 4.446299206644935,
        "iteration": 141,
        "root_gap": 1.1563305558688977,
        "root_lower": 2.845338730111544,
        "root_upper": 4.001669285980442
      },
      {
        "elapsed_seconds": 566.2758481502533,
        "initial_gap": 1.2848117287432197,
        "initial_lower_objective": 3.1614874779017157,
        "initial_upper_objective": 4.446299206644935,
        "iteration": 142,
        "root_gap": 1.1563305558688977,
        "root_lower": 2.845338730111544,
        "root_upper": 4.001669285980442
      },
      {
        "elapsed_seconds": 578.1339709758759,
        "initial_gap": 1.2848117287432197,
        "initial_lower_objective": 3.1614874779017157,
        "initial_upper_objective": 4.446299206644935,
        "iteration": 143,
        "root_gap": 1.1563305558688977,
        "root_lower": 2.845338730111544,
        "root_upper": 4.001669285980442
      },
      {
        "elapsed_seconds": 589.8942451477051,
        "initial_gap": 1.2848117287432197,
        "initial_lower_objective": 3.1614874779017157,
        "initial_upper_objective": 4.446299206644935,
        "iteration": 144,
        "root_gap": 1.1563305558688977,
        "root_lower": 2.845338730111544,
        "root_upper": 4.001669285980442
      },
      {
        "elapsed_seconds": 602.7397270202637,
        "initial_gap": 1.2848117287432197,
        "initial_lower_objective": 3.1614874779017157,
        "initial_upper_objective": 4.446299206644935,
        "iteration": 145,
        "root_gap": 1.1563305558688977,
        "root_lower": 2.845338730111544,
        "root_upper": 4.001669285980442
      },
      {
        "elapsed_seconds": 615.4711320400238,
        "initial_gap": 1.2848117116211577,
        "initial_lower_objective": 3.1614874950237772,
        "initial_upper_objective": 4.446299206644935,
        "iteration": 146,
        "root_gap": 1.156330540459042,
        "root_lower": 2.8453387455213996,
        "root_upper": 4.001669285980442
      },
      {
        "elapsed_seconds": 629.1184170246124,
        "initial_gap": 1.284811664547376,
        "initial_lower_objective": 3.161487542097559,
        "initial_upper_objective": 4.446299206644935,
        "iteration": 147,
        "root_gap": 1.1563304980926383,
        "root_lower": 2.8453387878878034,
        "root_upper": 4.001669285980442
      },
      {
        "elapsed_seconds": 631.5355920791626,
        "initial_gap": 1.284811664547376,
        "initial_lower_objective": 3.161487542097559,
        "initial_upper_objective": 4.446299206644935,
        "iteration": 148,
        "root_gap": 1.1563304980926383,
        "root_lower": 2.8453387878878034,
        "root_upper": 4.001669285980442
      },
      {
        "elapsed_seconds": 644.4598259925842,
        "initial_gap": 1.2848116277110389,
        "initial_lower_objective": 3.161487578933896,
        "initial_upper_objective": 4.446299206644935,
        "iteration": 149,
        "root_gap": 1.156330464939935,
        "root_lower": 2.8453388210405066,
        "root_upper": 4.001669285980442
      },
      {
        "elapsed_seconds": 658.1374790668488,
        "initial_gap": 1.2848116277110389,
        "initial_lower_objective": 3.161487578933896,
        "initial_upper_objective": 4.446299206644935,
        "iteration": 150,
        "root_gap": 1.156330464939935,
        "root_lower": 2.8453388210405066,
        "root_upper": 4.001669285980442
      },
      {
        "elapsed_seconds": 671.7475891113281,
        "initial_gap": 1.2848116277110389,
        "initial_lower_objective": 3.161487578933896,
        "initial_upper_objective": 4.446299206644935,
        "iteration": 151,
        "root_gap": 1.156330464939935,
        "root_lower": 2.8453388210405066,
        "root_upper": 4.001669285980442
      },
      {
        "elapsed_seconds": 680.9336221218109,
        "initial_gap": 1.2848116277110389,
        "initial_lower_objective": 3.161487578933896,
        "initial_upper_objective": 4.446299206644935,
        "iteration": 152,
        "root_gap": 1.156330464939935,
        "root_lower": 2.8453388210405066,
        "root_upper": 4.001669285980442
      },
      {
        "elapsed_seconds": 692.2619700431824,
        "initial_gap": 1.2735233184908321,
        "initial_lower_objective": 3.161487578933896,
        "initial_upper_objective": 4.435010897424728,
        "iteration": 153,
        "root_gap": 1.1461709866417489,
        "root_lower": 2.8453388210405066,
        "root_upper": 3.9915098076822555
      },
      {
        "elapsed_seconds": 703.2330451011658,
        "initial_gap": 1.2735233184908321,
        "initial_lower_objective": 3.161487578933896,
        "initial_upper_objective": 4.435010897424728,
        "iteration": 154,
        "root_gap": 1.1461709866417489,
        "root_lower": 2.8453388210405066,
        "root_upper": 3.9915098076822555
      }
    ],
    "initial_lower_residual": 8.500225412433338e-09,
    "initial_lower_subsolution_shift": 8.500225412433339e-08,
    "initial_upper_bound": "fully_observable",
    "initial_upper_iterations": 157,
    "initial_upper_residual": 9.137148815341334e-09,
    "initialization_seconds": 0.3128848075866699,
    "iterations": 154,
    "stop_reason": "max_time"
  }
}